inovonics/cloud/datastore/__init__.py
inovonics/cloud/datastore/__version__.py
inovonics/cloud/datastore/bases.py
inovonics/cloud/datastore/exceptions.py
inovonics/cloud/datastore/inoredis.py
inovonics_cloud_datastore-0.1.0.11.dist-info/DESCRIPTION.rst
inovonics_cloud_datastore-0.1.0.11.dist-info/METADATA
inovonics_cloud_datastore-0.1.0.11.dist-info/RECORD
inovonics_cloud_datastore-0.1.0.11.dist-info/WHEEL
inovonics_cloud_datastore-0.1.0.11.dist-info/metadata.json
inovonics_cloud_datastore-0.1.0.11.dist-info/top_level.txt
