Metadata-Version: 2.0
Name: inovonics-cloud-datastore
Version: 0.1.0.11
Summary: Basic classes for building a datastore using Redis as a backend.
Home-page: https://github.com/inovonics/cloud-datastore
Author: Daniel Williams
Author-email: dwilliams@inovonics.com
License: MIT
Platform: UNKNOWN
Classifier: Development Status :: 4 - Beta
Classifier: Environment :: Web Environment
Classifier: Intended Audience :: Developers
Classifier: License :: OSI Approved
Classifier: License :: OSI Approved :: MIT License
Classifier: Operating System :: POSIX
Classifier: Operating System :: POSIX :: Linux
Classifier: Programming Language :: Python
Classifier: Programming Language :: Python :: 3.5
Classifier: Programming Language :: Python :: 3.6
Classifier: Topic :: Internet :: WWW/HTTP :: Dynamic Content
Classifier: Topic :: Software Development :: Libraries :: Python Modules
Requires-Dist: python-dateutil (>=2.5.3)
Requires-Dist: redis (>=2.10)
Requires-Dist: redpipe (>=1.0)
